[{"name": "bench_climatologies.Bench_calendar_average.time_calendar_average", "idx": null, "pretty_name": "bench_climatologies.Bench_calendar_average.time_calendar_average", "last_rev": 3447, "last_value": 0.4656195695000065, "last_err": 0.008730926050154188, "prev_value": null, "change_rev": null}, {"name": "bench_climatologies.Bench_climate_anomaly.time_climate_anomaly", "idx": null, "pretty_name": "bench_climatologies.Bench_climate_anomaly.time_climate_anomaly", "last_rev": 3447, "last_value": 0.041430251999997836, "last_err": 0.0, "prev_value": 0.0378777370000023, "change_rev": [3431, 3447]}, {"name": "bench_climatologies.Bench_climatology_average.time_climatology_average", "idx": null, "pretty_name": "bench_climatologies.Bench_climatology_average.time_climatology_average", "last_rev": 3447, "last_value": 0.05656784700005346, "last_err": 0.0, "prev_value": 0.049182493499955626, "change_rev": [3431, 3447]}, {"name": "bench_climatologies.Bench_month_to_season.time_month_to_season", "idx": null, "pretty_name": "bench_climatologies.Bench_month_to_season.time_month_to_season", "last_rev": 3447, "last_value": 0.010655455000005531, "last_err": 0.0, "prev_value": 0.008632805500013774, "change_rev": [3431, 3447]}, {"name": "bench_fourier.Bench_fourier.peakmem_band_block", "idx": null, "pretty_name": "bench_fourier.Bench_fourier.peakmem_band_block", "last_rev": 3447, "last_value": 510185472.0, "last_err": 0.0, "prev_value": 510439424.0, "change_rev": [3431, 3447]}, {"name": "bench_fourier.Bench_fourier.time_band_block", "idx": null, "pretty_name": "bench_fourier.Bench_fourier.time_band_block", "last_rev": 3447, "last_value": 0.1550253409999982, "last_err": 0.0, "prev_value": 0.14345091999999227, "change_rev": [3431, 3447]}, {"name": "bench_interpolation.Bench_interp_hybrid_to_pressure.peakmem_interp_hybrid_to_pressure", "idx": null, "pretty_name": "bench_interpolation.Bench_interp_hybrid_to_pressure.peakmem_interp_hybrid_to_pressure", "last_rev": 3447, "last_value": 263467008.0, "last_err": 0.0, "prev_value": 263487488.0, "change_rev": [3431, 3447]}, {"name": "bench_interpolation.Bench_interp_hybrid_to_pressure.time_interp_hybrid_to_pressure", "idx": null, "pretty_name": "bench_interpolation.Bench_interp_hybrid_to_pressure.time_interp_hybrid_to_pressure", "last_rev": 3447, "last_value": 0.0404004795000219, "last_err": 0.0, "prev_value": 0.0379324634999989, "change_rev": [3431, 3447]}, {"name": "bench_interpolation.Bench_interp_hybrid_to_pressure_extrap_temp.peakmem_interp_hybrid_to_pressure_extrap_temp", "idx": null, "pretty_name": "bench_interpolation.Bench_interp_hybrid_to_pressure_extrap_temp.peakmem_interp_hybrid_to_pressure_extrap_temp", "last_rev": 3447, "last_value": 253341696.0, "last_err": 0.0, "prev_value": 253554688.0, "change_rev": [3431, 3447]}, {"name": "bench_interpolation.Bench_interp_hybrid_to_pressure_extrap_temp.time_interp_hybrid_to_pressure_extrap_temp", "idx": null, "pretty_name": "bench_interpolation.Bench_interp_hybrid_to_pressure_extrap_temp.time_interp_hybrid_to_pressure_extrap_temp", "last_rev": 3447, "last_value": 0.02333766399999604, "last_err": 0.0, "prev_value": 0.021244679999995242, "change_rev": [3431, 3447]}, {"name": "bench_interpolation.Bench_interp_multidim.peakmem_interp_multidim_chunk", "idx": null, "pretty_name": "bench_interpolation.Bench_interp_multidim.peakmem_interp_multidim_chunk", "last_rev": 3447, "last_value": 719511552.0, "last_err": 0.0, "prev_value": 719736832.0, "change_rev": [3431, 3447]}, {"name": "bench_interpolation.Bench_interp_multidim.time_interp_multidim_chunk", "idx": null, "pretty_name": "bench_interpolation.Bench_interp_multidim.time_interp_multidim_chunk", "last_rev": 3447, "last_value": 4.759046366000007, "last_err": 0.0, "prev_value": 4.25319574599996, "change_rev": [3431, 3447]}, {"name": "bench_interpolation.Bench_interp_sigma_to_hybrid.time_interp_sigma_to_hybrid_1d", "idx": null, "pretty_name": "bench_interpolation.Bench_interp_sigma_to_hybrid.time_interp_sigma_to_hybrid_1d", "last_rev": 3447, "last_value": 0.004154323666663609, "last_err": 0.0, "prev_value": 0.0037449526666838056, "change_rev": [3431, 3447]}, {"name": "bench_interpolation.Bench_interp_sigma_to_hybrid.time_interp_sigma_to_hybrid_3d", "idx": null, "pretty_name": "bench_interpolation.Bench_interp_sigma_to_hybrid.time_interp_sigma_to_hybrid_3d", "last_rev": 3447, "last_value": 0.01673833199998853, "last_err": 8.832794697017932e-05, "prev_value": null, "change_rev": null}, {"name": "bench_meteorology.Bench_actual_saturation_vapor_pressure.time_actual_saturation_vapor_pressure", "idx": null, "pretty_name": "bench_meteorology.Bench_actual_saturation_vapor_pressure.time_actual_saturation_vapor_pressure", "last_rev": 3447, "last_value": 1.0006663398671509e-05, "last_err": 0.0, "prev_value": 9.89854909092132e-06, "change_rev": [3431, 3447]}, {"name": "bench_meteorology.Bench_delta_pressure.time_delta_pressure", "idx": null, "pretty_name": "bench_meteorology.Bench_delta_pressure.time_delta_pressure", "last_rev": 3447, "last_value": 1.95684003906349e-05, "last_err": 5.378354951073707e-07, "prev_value": null, "change_rev": null}, {"name": "bench_meteorology.Bench_dewtemp.time_dewtemp", "idx": null, "pretty_name": "bench_meteorology.Bench_dewtemp.time_dewtemp", "last_rev": 3447, "last_value": 2.0361138733716305e-05, "last_err": 0.0, "prev_value": 1.9749341904787885e-05, "change_rev": [3431, 3447]}, {"name": "bench_meteorology.Bench_heat_index.time_heat_index", "idx": null, "pretty_name": "bench_meteorology.Bench_heat_index.time_heat_index", "last_rev": 3447, "last_value": 0.00023805289772708835, "last_err": 3.071396355316735e-06, "prev_value": null, "change_rev": null}, {"name": "bench_meteorology.Bench_max_daylight.time_max_daylight", "idx": null, "pretty_name": "bench_meteorology.Bench_max_daylight.time_max_daylight", "last_rev": 3447, "last_value": 0.0003160696176477733, "last_err": 1.2341667194813477e-06, "prev_value": null, "change_rev": null}, {"name": "bench_meteorology.Bench_psychrometric_constant.time_psychrometric_constant", "idx": null, "pretty_name": "bench_meteorology.Bench_psychrometric_constant.time_psychrometric_constant", "last_rev": 3447, "last_value": 1.3984307301419866e-06, "last_err": 0.0, "prev_value": 1.334759166772137e-06, "change_rev": [3431, 3447]}, {"name": "bench_meteorology.Bench_relhum.time_relhum", "idx": null, "pretty_name": "bench_meteorology.Bench_relhum.time_relhum", "last_rev": 3447, "last_value": 2.8731429155288786e-05, "last_err": 0.0, "prev_value": 2.7797391820464845e-05, "change_rev": [3431, 3447]}, {"name": "bench_meteorology.Bench_saturation_vapor_pressure.time_saturation_vapor_pressure", "idx": null, "pretty_name": "bench_meteorology.Bench_saturation_vapor_pressure.time_saturation_vapor_pressure", "last_rev": 3447, "last_value": 9.928434495773975e-06, "last_err": 0.0, "prev_value": 9.517659090880154e-06, "change_rev": [3431, 3447]}, {"name": "bench_meteorology.Bench_saturation_vapor_pressure_slope.time_saturation_vapor_pressure_slope", "idx": null, "pretty_name": "bench_meteorology.Bench_saturation_vapor_pressure_slope.time_saturation_vapor_pressure_slope", "last_rev": 3447, "last_value": 1.2965512789254336e-05, "last_err": 0.0, "prev_value": 1.236478278222892e-05, "change_rev": [3431, 3447]}, {"name": "bench_spherical.Bench_spherical.peakmem_decomposition", "idx": null, "pretty_name": "bench_spherical.Bench_spherical.peakmem_decomposition", "last_rev": 3447, "last_value": 344395776.0, "last_err": 0.0, "prev_value": 344576000.0, "change_rev": [3431, 3447]}, {"name": "bench_spherical.Bench_spherical.peakmem_recomposition", "idx": null, "pretty_name": "bench_spherical.Bench_spherical.peakmem_recomposition", "last_rev": 3447, "last_value": 305463296.0, "last_err": 0.0, "prev_value": 305618944.0, "change_rev": [3431, 3447]}, {"name": "bench_spherical.Bench_spherical.peakmem_scale_voronoi", "idx": null, "pretty_name": "bench_spherical.Bench_spherical.peakmem_scale_voronoi", "last_rev": 3447, "last_value": 229158912.0, "last_err": 0.0, "prev_value": 229523456.0, "change_rev": [3431, 3447]}, {"name": "bench_spherical.Bench_spherical.time_decomposition", "idx": null, "pretty_name": "bench_spherical.Bench_spherical.time_decomposition", "last_rev": 3447, "last_value": 2.154707808000012, "last_err": 0.0, "prev_value": 2.1427272349999384, "change_rev": [3431, 3447]}, {"name": "bench_spherical.Bench_spherical.time_recomposition", "idx": null, "pretty_name": "bench_spherical.Bench_spherical.time_recomposition", "last_rev": 3447, "last_value": 2.1607190779999996, "last_err": 0.0, "prev_value": 2.152427343999989, "change_rev": [3431, 3447]}, {"name": "bench_spherical.Bench_spherical.time_scale_voronoi", "idx": null, "pretty_name": "bench_spherical.Bench_spherical.time_scale_voronoi", "last_rev": 3447, "last_value": 0.24315765500000452, "last_err": 0.02280184763094888, "prev_value": null, "change_rev": null}, {"name": "bench_stats.Bench_eofunc_eofs.peakmem_eofunc", "idx": null, "pretty_name": "bench_stats.Bench_eofunc_eofs.peakmem_eofunc", "last_rev": 3447, "last_value": 209809408.0, "last_err": 0.0, "prev_value": 209752064.0, "change_rev": [3431, 3447]}, {"name": "bench_stats.Bench_eofunc_eofs.time_eofunc", "idx": null, "pretty_name": "bench_stats.Bench_eofunc_eofs.time_eofunc", "last_rev": 3447, "last_value": 0.01161144350004406, "last_err": 0.0, "prev_value": 0.010417177500016805, "change_rev": [3431, 3447]}, {"name": "bench_stats.Bench_eofunc_ps.peakmem_eofunc_ps", "idx": null, "pretty_name": "bench_stats.Bench_eofunc_ps.peakmem_eofunc_ps", "last_rev": 3447, "last_value": 415899648.0, "last_err": 0.0, "prev_value": 416112640.0, "change_rev": [3431, 3447]}, {"name": "bench_stats.Bench_eofunc_ps.time_eofunc_ps", "idx": null, "pretty_name": "bench_stats.Bench_eofunc_ps.time_eofunc_ps", "last_rev": 3447, "last_value": 0.3821980495000048, "last_err": 0.0, "prev_value": 0.3616570480000405, "change_rev": [3431, 3447]}, {"name": "bench_stats.Bench_pearson_r.time_pearson_r", "idx": null, "pretty_name": "bench_stats.Bench_pearson_r.time_pearson_r", "last_rev": 3447, "last_value": 5.79384481865055e-05, "last_err": 0.0, "prev_value": 5.803485919550074e-05, "change_rev": [3431, 3447]}, {"name": "import.Import.timeraw_import_geocat_comp", "idx": null, "pretty_name": "import.Import.timeraw_import_geocat_comp", "last_rev": 3447, "last_value": 1.78728801449995, "last_err": 0.032166811238086804, "prev_value": null, "change_rev": null}]