[{"name": "bench_climatologies.Bench_calendar_average.time_calendar_average", "idx": null, "pretty_name": "bench_climatologies.Bench_calendar_average.time_calendar_average", "last_rev": 3496, "last_value": 0.4741101730000139, "last_err": 0.008498902796073548, "prev_value": null, "change_rev": null}, {"name": "bench_climatologies.Bench_climate_anomaly.time_climate_anomaly", "idx": null, "pretty_name": "bench_climatologies.Bench_climate_anomaly.time_climate_anomaly", "last_rev": 3496, "last_value": 0.0378777370000023, "last_err": 0.0015550479718251095, "prev_value": null, "change_rev": null}, {"name": "bench_climatologies.Bench_climatology_average.time_climatology_average", "idx": null, "pretty_name": "bench_climatologies.Bench_climatology_average.time_climatology_average", "last_rev": 3496, "last_value": 0.047529998499982185, "last_err": 0.0013135872912810648, "prev_value": null, "change_rev": null}, {"name": "bench_climatologies.Bench_month_to_season.time_month_to_season", "idx": null, "pretty_name": "bench_climatologies.Bench_month_to_season.time_month_to_season", "last_rev": 3496, "last_value": 0.008591610250007875, "last_err": 0.00014639404434533727, "prev_value": null, "change_rev": null}, {"name": "bench_fourier.Bench_fourier.peakmem_band_block", "idx": null, "pretty_name": "bench_fourier.Bench_fourier.peakmem_band_block", "last_rev": 3496, "last_value": 510562304.0, "last_err": 194001.45454545456, "prev_value": null, "change_rev": null}, {"name": "bench_fourier.Bench_fourier.time_band_block", "idx": null, "pretty_name": "bench_fourier.Bench_fourier.time_band_block", "last_rev": 3496, "last_value": 0.14366031099996235, "last_err": 0.0023945035966287686, "prev_value": null, "change_rev": null}, {"name": "bench_interpolation.Bench_interp_hybrid_to_pressure.peakmem_interp_hybrid_to_pressure", "idx": null, "pretty_name": "bench_interpolation.Bench_interp_hybrid_to_pressure.peakmem_interp_hybrid_to_pressure", "last_rev": 3496, "last_value": 262205440.0, "last_err": 118198.85714285714, "prev_value": 263510016.0, "change_rev": [3454, 3463]}, {"name": "bench_interpolation.Bench_interp_hybrid_to_pressure.time_interp_hybrid_to_pressure", "idx": null, "pretty_name": "bench_interpolation.Bench_interp_hybrid_to_pressure.time_interp_hybrid_to_pressure", "last_rev": 3496, "last_value": 0.037504494499955854, "last_err": 0.0007317757707757569, "prev_value": null, "change_rev": null}, {"name": "bench_interpolation.Bench_interp_hybrid_to_pressure_extrap_temp.peakmem_interp_hybrid_to_pressure_extrap_temp", "idx": null, "pretty_name": "bench_interpolation.Bench_interp_hybrid_to_pressure_extrap_temp.peakmem_interp_hybrid_to_pressure_extrap_temp", "last_rev": 3496, "last_value": 256937984.0, "last_err": 142189.7142857143, "prev_value": 253356032.0, "change_rev": [3454, 3463]}, {"name": "bench_interpolation.Bench_interp_hybrid_to_pressure_extrap_temp.time_interp_hybrid_to_pressure_extrap_temp", "idx": null, "pretty_name": "bench_interpolation.Bench_interp_hybrid_to_pressure_extrap_temp.time_interp_hybrid_to_pressure_extrap_temp", "last_rev": 3496, "last_value": 0.020828020000010383, "last_err": 0.00035337399020376656, "prev_value": null, "change_rev": null}, {"name": "bench_interpolation.Bench_interp_multidim.peakmem_interp_multidim_chunk", "idx": null, "pretty_name": "bench_interpolation.Bench_interp_multidim.peakmem_interp_multidim_chunk", "last_rev": 3496, "last_value": 720044032.0, "last_err": 467688.7272727273, "prev_value": null, "change_rev": null}, {"name": "bench_interpolation.Bench_interp_multidim.time_interp_multidim_chunk", "idx": null, "pretty_name": "bench_interpolation.Bench_interp_multidim.time_interp_multidim_chunk", "last_rev": 3496, "last_value": 4.2094568505000325, "last_err": 0.2109899899043646, "prev_value": null, "change_rev": null}, {"name": "bench_interpolation.Bench_interp_sigma_to_hybrid.time_interp_sigma_to_hybrid_1d", "idx": null, "pretty_name": "bench_interpolation.Bench_interp_sigma_to_hybrid.time_interp_sigma_to_hybrid_1d", "last_rev": 3496, "last_value": 0.0036954518333232045, "last_err": 7.354986325915009e-05, "prev_value": null, "change_rev": null}, {"name": "bench_interpolation.Bench_interp_sigma_to_hybrid.time_interp_sigma_to_hybrid_3d", "idx": null, "pretty_name": "bench_interpolation.Bench_interp_sigma_to_hybrid.time_interp_sigma_to_hybrid_3d", "last_rev": 3496, "last_value": 0.016302618999986862, "last_err": 0.00040748119265360743, "prev_value": null, "change_rev": null}, {"name": "bench_meteorology.Bench_actual_saturation_vapor_pressure.time_actual_saturation_vapor_pressure", "idx": null, "pretty_name": "bench_meteorology.Bench_actual_saturation_vapor_pressure.time_actual_saturation_vapor_pressure", "last_rev": 3496, "last_value": 9.110695867752087e-06, "last_err": 2.5546052650736537e-07, "prev_value": null, "change_rev": null}, {"name": "bench_meteorology.Bench_delta_pressure.time_delta_pressure", "idx": null, "pretty_name": "bench_meteorology.Bench_delta_pressure.time_delta_pressure", "last_rev": 3496, "last_value": 1.9748652621714927e-05, "last_err": 4.5237850700199155e-07, "prev_value": null, "change_rev": null}, {"name": "bench_meteorology.Bench_dewtemp.time_dewtemp", "idx": null, "pretty_name": "bench_meteorology.Bench_dewtemp.time_dewtemp", "last_rev": 3496, "last_value": 1.990331262140457e-05, "last_err": 4.345230912705054e-07, "prev_value": null, "change_rev": null}, {"name": "bench_meteorology.Bench_heat_index.time_heat_index", "idx": null, "pretty_name": "bench_meteorology.Bench_heat_index.time_heat_index", "last_rev": 3496, "last_value": 0.0002352899456527864, "last_err": 3.3304458701784856e-06, "prev_value": null, "change_rev": null}, {"name": "bench_meteorology.Bench_max_daylight.time_max_daylight", "idx": null, "pretty_name": "bench_meteorology.Bench_max_daylight.time_max_daylight", "last_rev": 3496, "last_value": 0.00031491266176514646, "last_err": 1.574278061301833e-06, "prev_value": null, "change_rev": null}, {"name": "bench_meteorology.Bench_psychrometric_constant.time_psychrometric_constant", "idx": null, "pretty_name": "bench_meteorology.Bench_psychrometric_constant.time_psychrometric_constant", "last_rev": 3496, "last_value": 1.2956451403627994e-06, "last_err": 3.5983899947298e-08, "prev_value": null, "change_rev": null}, {"name": "bench_meteorology.Bench_relhum.time_relhum", "idx": null, "pretty_name": "bench_meteorology.Bench_relhum.time_relhum", "last_rev": 3496, "last_value": 2.6734038557302525e-05, "last_err": 5.650542644729543e-07, "prev_value": null, "change_rev": null}, {"name": "bench_meteorology.Bench_saturation_vapor_pressure.time_saturation_vapor_pressure", "idx": null, "pretty_name": "bench_meteorology.Bench_saturation_vapor_pressure.time_saturation_vapor_pressure", "last_rev": 3496, "last_value": 8.988065702473897e-06, "last_err": 1.6741925935837788e-07, "prev_value": null, "change_rev": null}, {"name": "bench_meteorology.Bench_saturation_vapor_pressure_slope.time_saturation_vapor_pressure_slope", "idx": null, "pretty_name": "bench_meteorology.Bench_saturation_vapor_pressure_slope.time_saturation_vapor_pressure_slope", "last_rev": 3496, "last_value": 1.1682905680647304e-05, "last_err": 2.924249293623573e-07, "prev_value": null, "change_rev": null}, {"name": "bench_spherical.Bench_spherical.peakmem_decomposition", "idx": null, "pretty_name": "bench_spherical.Bench_spherical.peakmem_decomposition", "last_rev": 3496, "last_value": 344780800.0, "last_err": 152669.0909090909, "prev_value": null, "change_rev": null}, {"name": "bench_spherical.Bench_spherical.peakmem_recomposition", "idx": null, "pretty_name": "bench_spherical.Bench_spherical.peakmem_recomposition", "last_rev": 3496, "last_value": 305876992.0, "last_err": 167936.0, "prev_value": null, "change_rev": null}, {"name": "bench_spherical.Bench_spherical.peakmem_scale_voronoi", "idx": null, "pretty_name": "bench_spherical.Bench_spherical.peakmem_scale_voronoi", "last_rev": 3496, "last_value": 229715968.0, "last_err": 218205.0909090909, "prev_value": null, "change_rev": null}, {"name": "bench_spherical.Bench_spherical.time_decomposition", "idx": null, "pretty_name": "bench_spherical.Bench_spherical.time_decomposition", "last_rev": 3496, "last_value": 2.1466213765000077, "last_err": 0.005445109751660525, "prev_value": null, "change_rev": null}, {"name": "bench_spherical.Bench_spherical.time_recomposition", "idx": null, "pretty_name": "bench_spherical.Bench_spherical.time_recomposition", "last_rev": 3496, "last_value": 2.147903607499984, "last_err": 0.005835479828069151, "prev_value": null, "change_rev": null}, {"name": "bench_spherical.Bench_spherical.time_scale_voronoi", "idx": null, "pretty_name": "bench_spherical.Bench_spherical.time_scale_voronoi", "last_rev": 3496, "last_value": 0.22735121050001794, "last_err": 0.01738107802207357, "prev_value": null, "change_rev": null}, {"name": "bench_stats.Bench_eofunc_eofs.peakmem_eofunc", "idx": null, "pretty_name": "bench_stats.Bench_eofunc_eofs.peakmem_eofunc", "last_rev": 3496, "last_value": 210235392.0, "last_err": 332520.7272727273, "prev_value": null, "change_rev": null}, {"name": "bench_stats.Bench_eofunc_eofs.time_eofunc", "idx": null, "pretty_name": "bench_stats.Bench_eofunc_eofs.time_eofunc", "last_rev": 3496, "last_value": 0.010429265999988502, "last_err": 0.00023425190883827543, "prev_value": null, "change_rev": null}, {"name": "bench_stats.Bench_eofunc_ps.peakmem_eofunc_ps", "idx": null, "pretty_name": "bench_stats.Bench_eofunc_ps.peakmem_eofunc_ps", "last_rev": 3496, "last_value": 416071680.0, "last_err": 210013.0909090909, "prev_value": null, "change_rev": null}, {"name": "bench_stats.Bench_eofunc_ps.time_eofunc_ps", "idx": null, "pretty_name": "bench_stats.Bench_eofunc_ps.time_eofunc_ps", "last_rev": 3496, "last_value": 0.3575108974999921, "last_err": 0.004696923795790508, "prev_value": null, "change_rev": null}, {"name": "bench_stats.Bench_pearson_r.time_pearson_r", "idx": null, "pretty_name": "bench_stats.Bench_pearson_r.time_pearson_r", "last_rev": 3496, "last_value": 5.681211436157877e-05, "last_err": 6.170120096129648e-07, "prev_value": null, "change_rev": null}, {"name": "import.Import.timeraw_import_geocat_comp", "idx": null, "pretty_name": "import.Import.timeraw_import_geocat_comp", "last_rev": 3496, "last_value": 1.8092946200000029, "last_err": 0.02836808821441022, "prev_value": 1.763957075999997, "change_rev": [3204, 3214]}]