[{"name": "bench_climatologies.Bench_calendar_average.time_calendar_average", "idx": null, "pretty_name": "bench_climatologies.Bench_calendar_average.time_calendar_average", "last_rev": 3573, "last_value": 0.47564813299999287, "last_err": 0.0054295706783301576, "prev_value": null, "change_rev": null}, {"name": "bench_climatologies.Bench_climate_anomaly.time_climate_anomaly", "idx": null, "pretty_name": "bench_climatologies.Bench_climate_anomaly.time_climate_anomaly", "last_rev": 3573, "last_value": 0.03966898000001606, "last_err": 0.0009264842264564044, "prev_value": null, "change_rev": null}, {"name": "bench_climatologies.Bench_climatology_average.time_climatology_average", "idx": null, "pretty_name": "bench_climatologies.Bench_climatology_average.time_climatology_average", "last_rev": 3573, "last_value": 0.047458135000027823, "last_err": 0.0009704195298528993, "prev_value": null, "change_rev": null}, {"name": "bench_climatologies.Bench_month_to_season.time_month_to_season", "idx": null, "pretty_name": "bench_climatologies.Bench_month_to_season.time_month_to_season", "last_rev": 3573, "last_value": 0.008615001499990171, "last_err": 0.0001209295133211114, "prev_value": null, "change_rev": null}, {"name": "bench_fourier.Bench_fourier.peakmem_band_block", "idx": null, "pretty_name": "bench_fourier.Bench_fourier.peakmem_band_block", "last_rev": 3573, "last_value": 510599168.0, "last_err": 544919.7037037037, "prev_value": null, "change_rev": null}, {"name": "bench_fourier.Bench_fourier.time_band_block", "idx": null, "pretty_name": "bench_fourier.Bench_fourier.time_band_block", "last_rev": 3573, "last_value": 0.14288513299999295, "last_err": 0.0019233256811209114, "prev_value": null, "change_rev": null}, {"name": "bench_interpolation.Bench_interp_hybrid_to_pressure.peakmem_interp_hybrid_to_pressure", "idx": null, "pretty_name": "bench_interpolation.Bench_interp_hybrid_to_pressure.peakmem_interp_hybrid_to_pressure", "last_rev": 3573, "last_value": 262397952.0, "last_err": 361965.037037037, "prev_value": null, "change_rev": null}, {"name": "bench_interpolation.Bench_interp_hybrid_to_pressure.time_interp_hybrid_to_pressure", "idx": null, "pretty_name": "bench_interpolation.Bench_interp_hybrid_to_pressure.time_interp_hybrid_to_pressure", "last_rev": 3573, "last_value": 0.037873229000013, "last_err": 0.0006362259661924766, "prev_value": null, "change_rev": null}, {"name": "bench_interpolation.Bench_interp_hybrid_to_pressure_extrap_temp.peakmem_interp_hybrid_to_pressure_extrap_temp", "idx": null, "pretty_name": "bench_interpolation.Bench_interp_hybrid_to_pressure_extrap_temp.peakmem_interp_hybrid_to_pressure_extrap_temp", "last_rev": 3573, "last_value": 257126400.0, "last_err": 436669.2173913043, "prev_value": 253376512.0, "change_rev": [3457, 3467]}, {"name": "bench_interpolation.Bench_interp_hybrid_to_pressure_extrap_temp.time_interp_hybrid_to_pressure_extrap_temp", "idx": null, "pretty_name": "bench_interpolation.Bench_interp_hybrid_to_pressure_extrap_temp.time_interp_hybrid_to_pressure_extrap_temp", "last_rev": 3573, "last_value": 0.02038914549999049, "last_err": 0.0004177509351217809, "prev_value": null, "change_rev": null}, {"name": "bench_interpolation.Bench_interp_multidim.peakmem_interp_multidim_chunk", "idx": null, "pretty_name": "bench_interpolation.Bench_interp_multidim.peakmem_interp_multidim_chunk", "last_rev": 3573, "last_value": 719753216.0, "last_err": 572529.7777777778, "prev_value": null, "change_rev": null}, {"name": "bench_interpolation.Bench_interp_multidim.time_interp_multidim_chunk", "idx": null, "pretty_name": "bench_interpolation.Bench_interp_multidim.time_interp_multidim_chunk", "last_rev": 3573, "last_value": 4.232833225999997, "last_err": 0.15983299257157246, "prev_value": null, "change_rev": null}, {"name": "bench_interpolation.Bench_interp_sigma_to_hybrid.time_interp_sigma_to_hybrid_1d", "idx": null, "pretty_name": "bench_interpolation.Bench_interp_sigma_to_hybrid.time_interp_sigma_to_hybrid_1d", "last_rev": 3573, "last_value": 0.0036280574999996893, "last_err": 6.420183045821984e-05, "prev_value": null, "change_rev": null}, {"name": "bench_interpolation.Bench_interp_sigma_to_hybrid.time_interp_sigma_to_hybrid_3d", "idx": null, "pretty_name": "bench_interpolation.Bench_interp_sigma_to_hybrid.time_interp_sigma_to_hybrid_3d", "last_rev": 3573, "last_value": 0.016102309999979525, "last_err": 0.0003518349122368036, "prev_value": null, "change_rev": null}, {"name": "bench_meteorology.Bench_actual_saturation_vapor_pressure.time_actual_saturation_vapor_pressure", "idx": null, "pretty_name": "bench_meteorology.Bench_actual_saturation_vapor_pressure.time_actual_saturation_vapor_pressure", "last_rev": 3573, "last_value": 9.133686776839725e-06, "last_err": 1.5488943616620433e-07, "prev_value": null, "change_rev": null}, {"name": "bench_meteorology.Bench_delta_pressure.time_delta_pressure", "idx": null, "pretty_name": "bench_meteorology.Bench_delta_pressure.time_delta_pressure", "last_rev": 3573, "last_value": 2.241235970468542e-05, "last_err": 3.184986188531891e-07, "prev_value": 1.964596348313087e-05, "change_rev": [3523, 3528]}, {"name": "bench_meteorology.Bench_dewtemp.time_dewtemp", "idx": null, "pretty_name": "bench_meteorology.Bench_dewtemp.time_dewtemp", "last_rev": 3573, "last_value": 2.0251880350181737e-05, "last_err": 3.6860464264259e-07, "prev_value": null, "change_rev": null}, {"name": "bench_meteorology.Bench_heat_index.time_heat_index", "idx": null, "pretty_name": "bench_meteorology.Bench_heat_index.time_heat_index", "last_rev": 3573, "last_value": 0.00023558210869583965, "last_err": 3.0158793862892704e-06, "prev_value": null, "change_rev": null}, {"name": "bench_meteorology.Bench_max_daylight.time_max_daylight", "idx": null, "pretty_name": "bench_meteorology.Bench_max_daylight.time_max_daylight", "last_rev": 3573, "last_value": 0.00031443751470640243, "last_err": 2.230386193907884e-06, "prev_value": null, "change_rev": null}, {"name": "bench_meteorology.Bench_psychrometric_constant.time_psychrometric_constant", "idx": null, "pretty_name": "bench_meteorology.Bench_psychrometric_constant.time_psychrometric_constant", "last_rev": 3573, "last_value": 1.2848297670007706e-06, "last_err": 2.653408900873511e-08, "prev_value": null, "change_rev": null}, {"name": "bench_meteorology.Bench_relhum.time_relhum", "idx": null, "pretty_name": "bench_meteorology.Bench_relhum.time_relhum", "last_rev": 3573, "last_value": 2.6751914215748008e-05, "last_err": 3.565298246277252e-07, "prev_value": null, "change_rev": null}, {"name": "bench_meteorology.Bench_saturation_vapor_pressure.time_saturation_vapor_pressure", "idx": null, "pretty_name": "bench_meteorology.Bench_saturation_vapor_pressure.time_saturation_vapor_pressure", "last_rev": 3573, "last_value": 8.998338842987374e-06, "last_err": 1.6982499220346504e-07, "prev_value": null, "change_rev": null}, {"name": "bench_meteorology.Bench_saturation_vapor_pressure_slope.time_saturation_vapor_pressure_slope", "idx": null, "pretty_name": "bench_meteorology.Bench_saturation_vapor_pressure_slope.time_saturation_vapor_pressure_slope", "last_rev": 3573, "last_value": 1.1697758776878645e-05, "last_err": 2.592445683197333e-07, "prev_value": null, "change_rev": null}, {"name": "bench_spherical.Bench_spherical.peakmem_decomposition", "idx": null, "pretty_name": "bench_spherical.Bench_spherical.peakmem_decomposition", "last_rev": 3573, "last_value": 344584192.0, "last_err": 313268.14814814815, "prev_value": null, "change_rev": null}, {"name": "bench_spherical.Bench_spherical.peakmem_recomposition", "idx": null, "pretty_name": "bench_spherical.Bench_spherical.peakmem_recomposition", "last_rev": 3573, "last_value": 305672192.0, "last_err": 313874.962962963, "prev_value": null, "change_rev": null}, {"name": "bench_spherical.Bench_spherical.peakmem_scale_voronoi", "idx": null, "pretty_name": "bench_spherical.Bench_spherical.peakmem_scale_voronoi", "last_rev": 3573, "last_value": 229621760.0, "last_err": 336933.9259259259, "prev_value": null, "change_rev": null}, {"name": "bench_spherical.Bench_spherical.time_decomposition", "idx": null, "pretty_name": "bench_spherical.Bench_spherical.time_decomposition", "last_rev": 3573, "last_value": 2.1478204114999926, "last_err": 0.004882822370611685, "prev_value": null, "change_rev": null}, {"name": "bench_spherical.Bench_spherical.time_recomposition", "idx": null, "pretty_name": "bench_spherical.Bench_spherical.time_recomposition", "last_rev": 3573, "last_value": 2.1500784240000144, "last_err": 0.005677526114247388, "prev_value": null, "change_rev": null}, {"name": "bench_spherical.Bench_spherical.time_scale_voronoi", "idx": null, "pretty_name": "bench_spherical.Bench_spherical.time_scale_voronoi", "last_rev": 3573, "last_value": 0.22521719549999375, "last_err": 0.01002596481291789, "prev_value": null, "change_rev": null}, {"name": "bench_stats.Bench_eofunc_eofs.peakmem_eofunc", "idx": null, "pretty_name": "bench_stats.Bench_eofunc_eofs.peakmem_eofunc", "last_rev": 3573, "last_value": 210202624.0, "last_err": 257744.59259259258, "prev_value": null, "change_rev": null}, {"name": "bench_stats.Bench_eofunc_eofs.time_eofunc", "idx": null, "pretty_name": "bench_stats.Bench_eofunc_eofs.time_eofunc", "last_rev": 3573, "last_value": 0.010418392000019594, "last_err": 0.00017794810869076622, "prev_value": null, "change_rev": null}, {"name": "bench_stats.Bench_eofunc_ps.peakmem_eofunc_ps", "idx": null, "pretty_name": "bench_stats.Bench_eofunc_ps.peakmem_eofunc_ps", "last_rev": 3573, "last_value": 416010240.0, "last_err": 223762.96296296295, "prev_value": null, "change_rev": null}, {"name": "bench_stats.Bench_eofunc_ps.time_eofunc_ps", "idx": null, "pretty_name": "bench_stats.Bench_eofunc_ps.time_eofunc_ps", "last_rev": 3573, "last_value": 0.36022015449998435, "last_err": 0.005266085392640113, "prev_value": null, "change_rev": null}, {"name": "bench_stats.Bench_pearson_r.time_pearson_r", "idx": null, "pretty_name": "bench_stats.Bench_pearson_r.time_pearson_r", "last_rev": 3573, "last_value": 5.6601986630887364e-05, "last_err": 1.0252456223000716e-06, "prev_value": null, "change_rev": null}, {"name": "import.Import.timeraw_import_geocat_comp", "idx": null, "pretty_name": "import.Import.timeraw_import_geocat_comp", "last_rev": 3573, "last_value": 1.8144857375000072, "last_err": 0.028608343960020755, "prev_value": 1.774226660500517, "change_rev": [3204, 3214]}]