[{"name": "bench_climatologies.Bench_calendar_average.time_calendar_average", "idx": null, "pretty_name": "bench_climatologies.Bench_calendar_average.time_calendar_average", "last_rev": 3471, "last_value": 0.4750377359999902, "last_err": 0.003722470516786535, "prev_value": null, "change_rev": null}, {"name": "bench_climatologies.Bench_climate_anomaly.time_climate_anomaly", "idx": null, "pretty_name": "bench_climatologies.Bench_climate_anomaly.time_climate_anomaly", "last_rev": 3471, "last_value": 0.038176336499986974, "last_err": 0.0009366659446303058, "prev_value": null, "change_rev": null}, {"name": "bench_climatologies.Bench_climatology_average.time_climatology_average", "idx": null, "pretty_name": "bench_climatologies.Bench_climatology_average.time_climatology_average", "last_rev": 3471, "last_value": 0.04791529199997058, "last_err": 0.0009953356011291362, "prev_value": null, "change_rev": null}, {"name": "bench_climatologies.Bench_month_to_season.time_month_to_season", "idx": null, "pretty_name": "bench_climatologies.Bench_month_to_season.time_month_to_season", "last_rev": 3471, "last_value": 0.008686834000002364, "last_err": 0.00010959096293254502, "prev_value": null, "change_rev": null}, {"name": "bench_fourier.Bench_fourier.peakmem_band_block", "idx": null, "pretty_name": "bench_fourier.Bench_fourier.peakmem_band_block", "last_rev": 3471, "last_value": 510513152.0, "last_err": 487424.0, "prev_value": null, "change_rev": null}, {"name": "bench_fourier.Bench_fourier.time_band_block", "idx": null, "pretty_name": "bench_fourier.Bench_fourier.time_band_block", "last_rev": 3471, "last_value": 0.1421878790000335, "last_err": 0.0014748608387310726, "prev_value": null, "change_rev": null}, {"name": "bench_interpolation.Bench_interp_hybrid_to_pressure.peakmem_interp_hybrid_to_pressure", "idx": null, "pretty_name": "bench_interpolation.Bench_interp_hybrid_to_pressure.peakmem_interp_hybrid_to_pressure", "last_rev": 3471, "last_value": 263393280.0, "last_err": 586898.2857142857, "prev_value": null, "change_rev": null}, {"name": "bench_interpolation.Bench_interp_hybrid_to_pressure.time_interp_hybrid_to_pressure", "idx": null, "pretty_name": "bench_interpolation.Bench_interp_hybrid_to_pressure.time_interp_hybrid_to_pressure", "last_rev": 3471, "last_value": 0.03773656799995706, "last_err": 0.0005310373292737302, "prev_value": null, "change_rev": null}, {"name": "bench_interpolation.Bench_interp_hybrid_to_pressure_extrap_temp.peakmem_interp_hybrid_to_pressure_extrap_temp", "idx": null, "pretty_name": "bench_interpolation.Bench_interp_hybrid_to_pressure_extrap_temp.peakmem_interp_hybrid_to_pressure_extrap_temp", "last_rev": 3471, "last_value": 256983040.0, "last_err": 197973.33333333334, "prev_value": 253376512.0, "change_rev": [3454, 3466]}, {"name": "bench_interpolation.Bench_interp_hybrid_to_pressure_extrap_temp.time_interp_hybrid_to_pressure_extrap_temp", "idx": null, "pretty_name": "bench_interpolation.Bench_interp_hybrid_to_pressure_extrap_temp.time_interp_hybrid_to_pressure_extrap_temp", "last_rev": 3471, "last_value": 0.020969671499983633, "last_err": 0.0003222378971641483, "prev_value": null, "change_rev": null}, {"name": "bench_interpolation.Bench_interp_multidim.peakmem_interp_multidim_chunk", "idx": null, "pretty_name": "bench_interpolation.Bench_interp_multidim.peakmem_interp_multidim_chunk", "last_rev": 3471, "last_value": 719613952.0, "last_err": 722066.2857142857, "prev_value": null, "change_rev": null}, {"name": "bench_interpolation.Bench_interp_multidim.time_interp_multidim_chunk", "idx": null, "pretty_name": "bench_interpolation.Bench_interp_multidim.time_interp_multidim_chunk", "last_rev": 3471, "last_value": 4.272323844000027, "last_err": 0.11538791563135668, "prev_value": null, "change_rev": null}, {"name": "bench_interpolation.Bench_interp_sigma_to_hybrid.time_interp_sigma_to_hybrid_1d", "idx": null, "pretty_name": "bench_interpolation.Bench_interp_sigma_to_hybrid.time_interp_sigma_to_hybrid_1d", "last_rev": 3471, "last_value": 0.003631204333345295, "last_err": 5.844853261202457e-05, "prev_value": null, "change_rev": null}, {"name": "bench_interpolation.Bench_interp_sigma_to_hybrid.time_interp_sigma_to_hybrid_3d", "idx": null, "pretty_name": "bench_interpolation.Bench_interp_sigma_to_hybrid.time_interp_sigma_to_hybrid_3d", "last_rev": 3471, "last_value": 0.01623826200003009, "last_err": 0.00023089029006291648, "prev_value": null, "change_rev": null}, {"name": "bench_meteorology.Bench_actual_saturation_vapor_pressure.time_actual_saturation_vapor_pressure", "idx": null, "pretty_name": "bench_meteorology.Bench_actual_saturation_vapor_pressure.time_actual_saturation_vapor_pressure", "last_rev": 3471, "last_value": 9.218218181827482e-06, "last_err": 1.0988209499549575e-07, "prev_value": null, "change_rev": null}, {"name": "bench_meteorology.Bench_delta_pressure.time_delta_pressure", "idx": null, "pretty_name": "bench_meteorology.Bench_delta_pressure.time_delta_pressure", "last_rev": 3471, "last_value": 1.9770884403655096e-05, "last_err": 3.608080679731365e-07, "prev_value": null, "change_rev": null}, {"name": "bench_meteorology.Bench_dewtemp.time_dewtemp", "idx": null, "pretty_name": "bench_meteorology.Bench_dewtemp.time_dewtemp", "last_rev": 3471, "last_value": 1.987136711276144e-05, "last_err": 3.3135360621451016e-07, "prev_value": null, "change_rev": null}, {"name": "bench_meteorology.Bench_heat_index.time_heat_index", "idx": null, "pretty_name": "bench_meteorology.Bench_heat_index.time_heat_index", "last_rev": 3471, "last_value": 0.00023539468478277382, "last_err": 1.106413333865778e-06, "prev_value": 0.00024241637777701422, "change_rev": [3431, 3445]}, {"name": "bench_meteorology.Bench_max_daylight.time_max_daylight", "idx": null, "pretty_name": "bench_meteorology.Bench_max_daylight.time_max_daylight", "last_rev": 3471, "last_value": 0.00031399284848427646, "last_err": 7.29530268984526e-07, "prev_value": null, "change_rev": null}, {"name": "bench_meteorology.Bench_psychrometric_constant.time_psychrometric_constant", "idx": null, "pretty_name": "bench_meteorology.Bench_psychrometric_constant.time_psychrometric_constant", "last_rev": 3471, "last_value": 1.2656130866825032e-06, "last_err": 1.4243680694052344e-08, "prev_value": null, "change_rev": null}, {"name": "bench_meteorology.Bench_relhum.time_relhum", "idx": null, "pretty_name": "bench_meteorology.Bench_relhum.time_relhum", "last_rev": 3471, "last_value": 2.6651690176313927e-05, "last_err": 2.801639554423007e-07, "prev_value": null, "change_rev": null}, {"name": "bench_meteorology.Bench_saturation_vapor_pressure.time_saturation_vapor_pressure", "idx": null, "pretty_name": "bench_meteorology.Bench_saturation_vapor_pressure.time_saturation_vapor_pressure", "last_rev": 3471, "last_value": 9.092943388428608e-06, "last_err": 1.217151763771526e-07, "prev_value": null, "change_rev": null}, {"name": "bench_meteorology.Bench_saturation_vapor_pressure_slope.time_saturation_vapor_pressure_slope", "idx": null, "pretty_name": "bench_meteorology.Bench_saturation_vapor_pressure_slope.time_saturation_vapor_pressure_slope", "last_rev": 3471, "last_value": 1.1614833517672295e-05, "last_err": 3.903170994343705e-07, "prev_value": null, "change_rev": null}, {"name": "bench_spherical.Bench_spherical.peakmem_decomposition", "idx": null, "pretty_name": "bench_spherical.Bench_spherical.peakmem_decomposition", "last_rev": 3471, "last_value": 344850432.0, "last_err": 197778.2857142857, "prev_value": null, "change_rev": null}, {"name": "bench_spherical.Bench_spherical.peakmem_recomposition", "idx": null, "pretty_name": "bench_spherical.Bench_spherical.peakmem_recomposition", "last_rev": 3471, "last_value": 305868800.0, "last_err": 210651.42857142858, "prev_value": null, "change_rev": null}, {"name": "bench_spherical.Bench_spherical.peakmem_scale_voronoi", "idx": null, "pretty_name": "bench_spherical.Bench_spherical.peakmem_scale_voronoi", "last_rev": 3471, "last_value": 229675008.0, "last_err": 287305.14285714284, "prev_value": null, "change_rev": null}, {"name": "bench_spherical.Bench_spherical.time_decomposition", "idx": null, "pretty_name": "bench_spherical.Bench_spherical.time_decomposition", "last_rev": 3471, "last_value": 2.1456617325000025, "last_err": 0.004093133466213839, "prev_value": null, "change_rev": null}, {"name": "bench_spherical.Bench_spherical.time_recomposition", "idx": null, "pretty_name": "bench_spherical.Bench_spherical.time_recomposition", "last_rev": 3471, "last_value": 2.1488368944999934, "last_err": 0.00279873833090986, "prev_value": null, "change_rev": null}, {"name": "bench_spherical.Bench_spherical.time_scale_voronoi", "idx": null, "pretty_name": "bench_spherical.Bench_spherical.time_scale_voronoi", "last_rev": 3471, "last_value": 0.22597327550002433, "last_err": 0.006056925092838589, "prev_value": null, "change_rev": null}, {"name": "bench_stats.Bench_eofunc_eofs.peakmem_eofunc", "idx": null, "pretty_name": "bench_stats.Bench_eofunc_eofs.peakmem_eofunc", "last_rev": 3471, "last_value": 210046976.0, "last_err": 222354.2857142857, "prev_value": null, "change_rev": null}, {"name": "bench_stats.Bench_eofunc_eofs.time_eofunc", "idx": null, "pretty_name": "bench_stats.Bench_eofunc_eofs.time_eofunc", "last_rev": 3471, "last_value": 0.010425719500005926, "last_err": 0.00019763947138951731, "prev_value": null, "change_rev": null}, {"name": "bench_stats.Bench_eofunc_ps.peakmem_eofunc_ps", "idx": null, "pretty_name": "bench_stats.Bench_eofunc_ps.peakmem_eofunc_ps", "last_rev": 3471, "last_value": 415993856.0, "last_err": 104155.42857142857, "prev_value": null, "change_rev": null}, {"name": "bench_stats.Bench_eofunc_ps.time_eofunc_ps", "idx": null, "pretty_name": "bench_stats.Bench_eofunc_ps.time_eofunc_ps", "last_rev": 3471, "last_value": 0.36029383900000767, "last_err": 0.004437889091191334, "prev_value": null, "change_rev": null}, {"name": "bench_stats.Bench_pearson_r.time_pearson_r", "idx": null, "pretty_name": "bench_stats.Bench_pearson_r.time_pearson_r", "last_rev": 3471, "last_value": 5.746539285713889e-05, "last_err": 1.60079517131475e-06, "prev_value": null, "change_rev": null}, {"name": "import.Import.timeraw_import_geocat_comp", "idx": null, "pretty_name": "import.Import.timeraw_import_geocat_comp", "last_rev": 3471, "last_value": 1.817885590000003, "last_err": 0.026775596157316686, "prev_value": 1.774226660500517, "change_rev": [3204, 3214]}]