{"commit_hash": "84d9997b9b28414eb33c7a21e05fa88d9b232438", "env_name": "conda-py3.10", "date": 1741826155000, "params": {"arch": "x64", "cpu": "2-core unknown", "machine": "GH-Actions", "os": "ubuntu-latest", "ram": "7GB", "python": "3.10"}, "python": "3.10", "requirements": {}, "env_vars": {}, "result_columns": ["result", "params", "version", "started_at", "duration", "stats_ci_99_a", "stats_ci_99_b", "stats_q_25", "stats_q_75", "stats_number", "stats_repeat", "samples", "profile"], "results": {"import.Import.timeraw_import_geocat_comp": [[1.7702780760000678], [], "a31d189939828b73cd67532df40f01aebfe362b9fd831be60d8eef67ee309055", 1746122667318, 21.575, [1.7558], [1.8164], [1.765], [1.7854], [1], [8]]}, "durations": {"<build>": 26.787853479385376}, "version": 2}