{"commit_hash": "c6fe0005124d1f591b288650cb9c04c82502f86d", "env_name": "conda-py3.13", "date": 1750868047000, "params": {"arch": "x64", "cpu": "2-core unknown", "machine": "GH-Actions", "os": "ubuntu-latest", "ram": "7GB", "python": "3.13"}, "python": "3.13", "requirements": {}, "env_vars": {}, "result_columns": ["result", "params", "version", "started_at", "duration", "stats_ci_99_a", "stats_ci_99_b", "stats_q_25", "stats_q_75", "stats_number", "stats_repeat", "samples", "profile"], "results": {"import.Import.timeraw_import_geocat_comp": [[1.9380891060000067], [], "a31d189939828b73cd67532df40f01aebfe362b9fd831be60d8eef67ee309055", 1750868331360, 22.744, [1.9165], [1.973], [1.9325], [1.9638], [1], [7]]}, "durations": {"<build>": 27.256935119628906}, "version": 2}